imicpe/__init__.py
imicpe/_version.py
imicpe/cs/__init__.py
imicpe/cs/l1.py
imicpe/cs/masks.py
imicpe/cs/metrics.py
imicpe/cs/operators.py
imicpe/cs/shepp_logan_phantom.py
imicpe/cs/tikhonov.py
imicpe/optim/__init__.py
imicpe/optim/metrics.py
imicpe/optim/operators.py
imicpe/optim/pnnDataset.py
imicpe/optim/pnnTrainer.py
imicpe/optim/pnnUtils.py
imicpe/reco3D/__init__.py
imicpe/reco3D/angles.py
imicpe/reco3D/calculPose.py
imicpe/reco3D/evalTrajecto.py
imicpe/reco3D/vue3D.py
imicpe-1.0.9.dist-info/licenses/LICENSE
imicpe-1.0.9.dist-info/METADATA
imicpe-1.0.9.dist-info/WHEEL
imicpe-1.0.9.dist-info/top_level.txt
imicpe-1.0.9.dist-info/RECORD
