Metadata-Version: 2.4
Name: imicpe
Version: 1.0.9
Summary: Toolbox for Maths,Signal,Image Teaching @ CPE
Author-email: Marion Foare <marion.foare@cpe.fr>, Eric Van Reeth <eric.vanreeth@cpe.fr>, Arthur Gautheron <arthur.gautheron@cpe.fr>
License: MIT License
Project-URL: Homepage, https://www.cpe.fr
Project-URL: Documentation, https://cpe.pages.in2p3.fr/msi/toolbox_imi/
Classifier: Programming Language :: Python :: 3
Classifier: License :: OSI Approved :: MIT License
Classifier: Operating System :: OS Independent
Requires-Python: >=3.8
License-File: LICENSE
Requires-Dist: numpy
Requires-Dist: scipy
Requires-Dist: plotly
Requires-Dist: torch
Requires-Dist: torchvision
Requires-Dist: tqdm
Requires-Dist: PyWavelets
Requires-Dist: scikit-image
Dynamic: license-file
